{
  "recentFiles": [
    {
      "basename": "2023-04-20",
      "path": "2.等待处理/Diary/2023-04-20.md"
    },
    {
      "basename": "坐飞机注意事项",
      "path": "5.专题研究/南京旅游规划/坐飞机注意事项.md"
    },
    {
      "basename": "消费记录",
      "path": "5.专题研究/南京旅游规划/消费记录.md"
    },
    {
      "basename": "计划",
      "path": "5.专题研究/南京旅游规划/计划.md"
    },
    {
      "basename": "2023-16",
      "path": "4.归档/工作/学习周刊/2023-16.md"
    },
    {
      "basename": "AI产品目录",
      "path": "4.归档/学习/1.修身/AI产品/AI产品目录.md"
    },
    {
      "basename": "2023-15",
      "path": "4.归档/工作/学习周刊/2023-15.md"
    },
    {
      "basename": "2023-14",
      "path": "4.归档/工作/学习周刊/2023-14.md"
    },
    {
      "basename": "【浏览器使用技巧】",
      "path": "4.归档/生活/搜索/【浏览器使用技巧】.md"
    }
  ],
  "omittedPaths": [],
  "maxLength": 10,
  "openType": "tab"
}